README
setup.py
alioss.egg-info/PKG-INFO
alioss.egg-info/SOURCES.txt
alioss.egg-info/dependency_links.txt
alioss.egg-info/top_level.txt
oss/__init__.py
oss/oss_api.py
oss/oss_sample.py
oss/oss_util.py
oss/oss_xml_handler.py
oss/osscmd.py
oss/pkg_info.py