Metadata-Version: 1.0
Name: alioss
Version: 0.22.1
Summary: Command line tool for managing Aliyun Open Storage Service.
Home-page: http://www.phodal.com
Author: Phodal.Gmszone
Author-email: gmszone@gmail.com
License: GPL version 2
Platform: UNKNOWN
